{
    "398559841020411904": {
        "Level": 8,
        "XP": 228,
        "MaxXP": 450
    },
    "524024685646708736": {
        "Level": 1,
        "XP": 75,
        "MaxXP": 100
    },
    "704607867155513506": {
        "Level": 9,
        "XP": 123,
        "MaxXP": 500
    },
    "805608689293197322": {
        "Level": 1,
        "XP": 42,
        "MaxXP": 100
    },
    "437300638788091934": {
        "Level": 5,
        "XP": 87,
        "MaxXP": 300
    },
    "830085511690584074": {
        "Level": 2,
        "XP": 72,
        "MaxXP": 150
    },
    "731228330027647086": {
        "Level": 1,
        "XP": 48,
        "MaxXP": 100
    },
    "783037024801521685": {
        "Level": 1,
        "XP": 21,
        "MaxXP": 100
    },
    "760192017866817617": {
        "Level": 5,
        "XP": 207,
        "MaxXP": 300
    },
    "832041832048492544": {
        "Level": 1,
        "XP": 84,
        "MaxXP": 100
    },
    "604270073586122753": {
        "Level": 4,
        "XP": 81,
        "MaxXP": 250
    },
    "292876627409633284": {
        "Level": 1,
        "XP": 27,
        "MaxXP": 100
    },
    "407210852358422549": {
        "Level": 1,
        "XP": 12,
        "MaxXP": 100
    },
    "527132170637279249": {
        "Level": 1,
        "XP": 51,
        "MaxXP": 100
    },
    "548475504391487488": {
        "Level": 1,
        "XP": 75,
        "MaxXP": 100
    },
    "585092571315830784": {
        "Level": 2,
        "XP": 129,
        "MaxXP": 150
    },
    "331518951345487872": {
        "Level": 1,
        "XP": 3,
        "MaxXP": 100
    },
    "375732308558217229": {
        "Level": 1,
        "XP": 3,
        "MaxXP": 100
    },
    "758007557158731836": {
        "Level": 1,
        "XP": 69,
        "MaxXP": 100
    },
    "611876203548114944": {
        "Level": 1,
        "XP": 9,
        "MaxXP": 100
    },
    "593102634785832960": {
        "Level": 1,
        "XP": 3,
        "MaxXP": 100
    },
    "510016054391734273": {
        "Level": 2,
        "XP": 36,
        "MaxXP": 150
    },
    "637559675990310917": {
        "Level": 1,
        "XP": 6,
        "MaxXP": 100
    },
    "533313053484253204": {
        "Level": 1,
        "XP": 18,
        "MaxXP": 100
    },
    "548552174851063808": {
        "Level": 2,
        "XP": 0,
        "MaxXP": 150
    },
    "693943685720703069": {
        "Level": 1,
        "XP": 3,
        "MaxXP": 100
    },
    "426537812993638400": {
        "Level": 1,
        "XP": 18,
        "MaxXP": 100
    },
    "481810727460667403": {
        "Level": 1,
        "XP": 18,
        "MaxXP": 100
    },
    "397408418195046402": {
        "Level": 1,
        "XP": 3,
        "MaxXP": 100
    },
    "833321044135641119": {
        "Level": 1,
        "XP": 6,
        "MaxXP": 100
    },
    "482552772252794880": {
        "Level": 1,
        "XP": 15,
        "MaxXP": 100
    },
    "809627670379626557": {
        "Level": 1,
        "XP": 3,
        "MaxXP": 100
    },
    "776540316504555531": {
        "Level": 1,
        "XP": 3,
        "MaxXP": 100
    },
    "359823473864081408": {
        "Level": 1,
        "XP": 39,
        "MaxXP": 100
    },
    "721485320843034803": {
        "Level": 1,
        "XP": 57,
        "MaxXP": 100
    },
    "540802606784839680": {
        "Level": 1,
        "XP": 3,
        "MaxXP": 100
    },
    "789808040416378880": {
        "Level": 1,
        "XP": 3,
        "MaxXP": 100
    },
    "499678739609681920": {
        "Level": 1,
        "XP": 3,
        "MaxXP": 100
    },
    "505872504196169728": {
        "Level": 2,
        "XP": 33,
        "MaxXP": 150
    },
    "707770453258666055": {
        "Level": 1,
        "XP": 87,
        "MaxXP": 100
    },
    "755478415276245002": {
        "Level": 1,
        "XP": 3,
        "MaxXP": 100
    },
    "833778675622608928": {
        "Level": 1,
        "XP": 3,
        "MaxXP": 100
    },
    "825966120531787796": {
        "Level": 1,
        "XP": 51,
        "MaxXP": 100
    },
    "401615367564165122": {
        "Level": 1,
        "XP": 3,
        "MaxXP": 100
    },
    "345519367028736001": {
        "Level": 1,
        "XP": 6,
        "MaxXP": 100
    },
    "815105385148448808": {
        "Level": 1,
        "XP": 6,
        "MaxXP": 100
    },
    "340584252775202817": {
        "Level": 1,
        "XP": 6,
        "MaxXP": 100
    },
    "773640415517474896": {
        "Level": 1,
        "XP": 3,
        "MaxXP": 100
    },
    "698009679690727474": {
        "Level": 1,
        "XP": 6,
        "MaxXP": 100
    },
    "494256156751953921": {
        "Level": 1,
        "XP": 39,
        "MaxXP": 100
    },
    "751619437421002902": {
        "Level": 1,
        "XP": 6,
        "MaxXP": 100
    },
    "719809792197001237": {
        "Level": 2,
        "XP": 72,
        "MaxXP": 150
    },
    "673175401542975491": {
        "Level": 1,
        "XP": 6,
        "MaxXP": 100
    },
    "534127957141356544": {
        "Level": 1,
        "XP": 3,
        "MaxXP": 100
    },
    "634734262192701452": {
        "Level": 1,
        "XP": 33,
        "MaxXP": 100
    },
    "825205690451755038": {
        "Level": 1,
        "XP": 18,
        "MaxXP": 100
    },
    "294882584201003009": {
        "Level": 1,
        "XP": 15,
        "MaxXP": 100
    },
    "663995393452802069": {
        "Level": 1,
        "XP": 39,
        "MaxXP": 100
    },
    "404247830409248769": {
        "Level": 2,
        "XP": 99,
        "MaxXP": 150
    },
    "820554389332033556": {
        "Level": 1,
        "XP": 3,
        "MaxXP": 100
    },
    "812869200016179220": {
        "Level": 1,
        "XP": 3,
        "MaxXP": 100
    },
    "400059032666374145": {
        "Level": 1,
        "XP": 6,
        "MaxXP": 100
    },
    "830800138926030908": {
        "Level": 1,
        "XP": 30,
        "MaxXP": 100
    },
    "271859132355575811": {
        "Level": 1,
        "XP": 3,
        "MaxXP": 100
    },
    "790863994532397086": {
        "Level": 3,
        "XP": 36,
        "MaxXP": 200
    },
    "800363210792370176": {
        "Level": 1,
        "XP": 3,
        "MaxXP": 100
    },
    "503734470013353984": {
        "Level": 1,
        "XP": 6,
        "MaxXP": 100
    },
    "495608181968338965": {
        "Level": 2,
        "XP": 111,
        "MaxXP": 150
    },
    "564452103200833537": {
        "Level": 1,
        "XP": 6,
        "MaxXP": 100
    },
    "546702378636804097": {
        "Level": 1,
        "XP": 3,
        "MaxXP": 100
    },
    "332467390522589184": {
        "Level": 1,
        "XP": 15,
        "MaxXP": 100
    },
    "702873516122570792": {
        "Level": 1,
        "XP": 42,
        "MaxXP": 100
    },
    "705002266884571138": {
        "Level": 1,
        "XP": 36,
        "MaxXP": 100
    },
    "788048384111017997": {
        "Level": 1,
        "XP": 3,
        "MaxXP": 100
    },
    "374092703937593344": {
        "Level": 1,
        "XP": 3,
        "MaxXP": 100
    },
    "449768653710426142": {
        "Level": 1,
        "XP": 3,
        "MaxXP": 100
    },
    "471404299730288680": {
        "Level": 1,
        "XP": 3,
        "MaxXP": 100
    },
    "742814494673076334": {
        "Level": 1,
        "XP": 6,
        "MaxXP": 100
    },
    "775426036002324492": {
        "Level": 1,
        "XP": 3,
        "MaxXP": 100
    },
    "767513664471171072": {
        "Level": 1,
        "XP": 33,
        "MaxXP": 100
    },
    "199687970821767178": {
        "Level": 1,
        "XP": 9,
        "MaxXP": 100
    },
    "741394358762340393": {
        "Level": 1,
        "XP": 63,
        "MaxXP": 100
    },
    "659377055636652052": {
        "Level": 1,
        "XP": 3,
        "MaxXP": 100
    },
    "608068876693143573": {
        "Level": 1,
        "XP": 3,
        "MaxXP": 100
    },
    "781977054207803393": {
        "Level": 1,
        "XP": 9,
        "MaxXP": 100
    },
    "486973768485306381": {
        "Level": 1,
        "XP": 3,
        "MaxXP": 100
    },
    "367175315379847168": {
        "Level": 1,
        "XP": 3,
        "MaxXP": 100
    },
    "512923847587135499": {
        "Level": 1,
        "XP": 42,
        "MaxXP": 100
    },
    "800534440768962572": {
        "Level": 1,
        "XP": 15,
        "MaxXP": 100
    }
}